spirit_guess/__init__.py
spirit_guess/enchant_detect.py
spirit_guess/languages.py
spirit_guess/ngram_detect.py
spirit_guess/ngram_model.py
spirit_guess/orthography.py
spirit_guess/tokenize.py
spirit_guess-0.0.15.dist-info/LICENSE
spirit_guess-0.0.15.dist-info/METADATA
spirit_guess-0.0.15.dist-info/WHEEL
spirit_guess-0.0.15.dist-info/top_level.txt
spirit_guess-0.0.15.dist-info/RECORD
