Metadata-Version: 2.1
Name: spirit-guess
Version: 0.0.15
Summary: UNKNOWN
Home-page: https://github.com/alvations/spirit-guess
Author: Liling Tan
Author-email: UNKNOWN
License: MIT
Platform: UNKNOWN
Requires-Dist: pyenchant
